pyortal/EMS.py
pyortal/EMSAPIAuth.py
pyortal/UTM.py
pyortal/__init__.py
slink_pyortal-0.2.4.dist-info/METADATA
slink_pyortal-0.2.4.dist-info/WHEEL
slink_pyortal-0.2.4.dist-info/top_level.txt
slink_pyortal-0.2.4.dist-info/RECORD
