Metadata-Version: 2.4
Name: slink-pyortal
Version: 0.2.4
Summary: Control PORTAL operations programatically from Python
Author-email: Slink-Tech <sven@slink-tech.co.uk>
Project-URL: Homepage, https://github.com/SLiNK-TECH/portal-python-sdk
Classifier: License :: OSI Approved :: MIT License
Classifier: Programming Language :: Python
Classifier: Programming Language :: Python :: 3
Requires-Python: >=3.9
Requires-Dist: python-dotenv
Requires-Dist: requests>=2.25.1
Requires-Dist: google-api-python-client
Requires-Dist: websocket-client
Requires-Dist: tomli; python_version < "3.11"
